jsonasobj2/__init__.py
jsonasobj2/_jsonobj.py
jsonasobj2/extendednamespace.py
jsonasobj2-1.0.3.dist-info/AUTHORS
jsonasobj2-1.0.3.dist-info/METADATA
jsonasobj2-1.0.3.dist-info/WHEEL
jsonasobj2-1.0.3.dist-info/pbr.json
jsonasobj2-1.0.3.dist-info/top_level.txt
jsonasobj2-1.0.3.dist-info/RECORD
